cdd_flow/__init__.py
cdd_flow/cli.py
cdd_flow/commands/__init__.py
cdd_flow/commands/abandon.py
cdd_flow/commands/checkpoint.py
cdd_flow/commands/complete.py
cdd_flow/commands/ctx.py
cdd_flow/commands/history.py
cdd_flow/commands/land.py
cdd_flow/commands/start.py
cdd_flow/commands/status.py
cdd_flow/commands/undo.py
cdd_flow/commands/verify.py
cdd_flow/core/__init__.py
cdd_flow/core/config.py
cdd_flow/core/recovery.py
cdd_flow/core/session.py
cdd_flow-0.1.0.dist-info/METADATA
cdd_flow-0.1.0.dist-info/WHEEL
cdd_flow-0.1.0.dist-info/entry_points.txt
cdd_flow-0.1.0.dist-info/licenses/LICENSE
cdd_flow-0.1.0.dist-info/RECORD
