Metadata-Version: 2.4
Name: cdd-flow
Version: 0.1.0
Summary: AI-Assisted Development Delivery System
Project-URL: Homepage, https://github.com/thegdyne/cdd-flow
Project-URL: Repository, https://github.com/thegdyne/cdd-flow
Project-URL: Documentation, https://github.com/thegdyne/cdd-flow/blob/main/SPEC.md
Author: Gareth Dyne
License-Expression: MIT
License-File: LICENSE
Keywords: ai-development,automation,cdd,contract-driven-development,workflow
Classifier: Development Status :: 3 - Alpha
Classifier: Environment :: Console
Classifier: Intended Audience :: Developers
Classifier: License :: OSI Approved :: MIT License
Classifier: Operating System :: MacOS
Classifier: Programming Language :: Python :: 3
Classifier: Programming Language :: Python :: 3.10
Classifier: Programming Language :: Python :: 3.11
Classifier: Programming Language :: Python :: 3.12
Classifier: Topic :: Software Development
Classifier: Topic :: Software Development :: Build Tools
Requires-Python: >=3.10
Requires-Dist: click>=8.0
Requires-Dist: pyyaml>=6.0
Requires-Dist: rich>=13.0
Provides-Extra: dev
Requires-Dist: pytest-cov>=4.0; extra == 'dev'
Requires-Dist: pytest>=7.0; extra == 'dev'
Requires-Dist: ruff>=0.1.0; extra == 'dev'
Provides-Extra: full
Requires-Dist: cdd-context>=0.3.0; extra == 'full'
Requires-Dist: cdd-tooling>=0.1.1; extra == 'full'
